barfi/__init__.py
barfi/config.py
barfi/flow/__init__.py
barfi/flow/block/__init__.py
barfi/flow/block/base.py
barfi/flow/block/interface.py
barfi/flow/block/option.py
barfi/flow/block/prepare.py
barfi/flow/compute/__init__.py
barfi/flow/compute/base.py
barfi/flow/schema/__init__.py
barfi/flow/schema/manage.py
barfi/flow/schema/types.py
barfi/flow/streamlit/__init__.py
barfi/flow/streamlit/base.py
barfi/flow/streamlit/static/assets/index-D_TASKN1.js
barfi/flow/streamlit/static/assets/index-Lv3-tbfn.css
barfi/flow/streamlit/static/index.html
barfi/flow/streamlit/types.py
barfi/utils/__init__.py
barfi/utils/v0_migration.py
barfi/v0/__init__.py
barfi/v0/block_builder.py
barfi/v0/component.py
barfi/v0/compute_engine.py
barfi/v0/manage_schema.py
barfi/v0/option_builder.py
barfi/v0/static/css/app.51aff32b.css
barfi/v0/static/index.html
barfi/v0/static/js/app.4b1442b7.js
barfi/v0/static/js/app.4b1442b7.js.map
barfi/v0/static/js/chunk-vendors.eb7fca41.js
barfi/v0/static/js/chunk-vendors.eb7fca41.js.map
barfi-1.1.0.dist-info/LICENSE
barfi-1.1.0.dist-info/METADATA
barfi-1.1.0.dist-info/WHEEL
barfi-1.1.0.dist-info/RECORD
