Metadata-Version: 2.3
Name: barfi
Version: 1.1.0
Summary: Framework for building custom visual no-code workflows for AI and data apps. Also commonly known as: graphical flow based programming framework
License: Apache-2.0
Keywords: no-code,framework,streamlit,graphical programming,AI,LLM
Author: Adithya Krishnan
Author-email: krishsandeep@gmail.com
Requires-Python: >=3.9,!=3.9.7
Classifier: Development Status :: 3 - Alpha
Classifier: Programming Language :: Python :: 3
Classifier: Operating System :: OS Independent
Provides-Extra: deprecated-v0
Provides-Extra: streamlit
Requires-Dist: networkx (>=3.1) ; extra == "deprecated-v0"
Requires-Dist: streamlit (>=1.0.0) ; extra == "streamlit"
Requires-Dist: streamlit (>=1.37.1) ; extra == "deprecated-v0"
